accretion_cli/__init__.py
accretion_cli/_commands/__init__.py
accretion_cli/_commands/add.py
accretion_cli/_commands/destroy.py
accretion_cli/_commands/init.py
accretion_cli/_commands/publish.py
accretion_cli/_commands/raw/__init__.py
accretion_cli/_commands/raw/init.py
accretion_cli/_commands/raw/add/__init__.py
accretion_cli/_commands/raw/add/artifact_builder.py
accretion_cli/_commands/raw/add/builders.py
accretion_cli/_commands/raw/add/layer_builder.py
accretion_cli/_commands/raw/add/regions.py
accretion_cli/_commands/update/__init__.py
accretion_cli/_commands/update/all.py
accretion_cli/_templates/__init__.py
accretion_cli/_templates/artifact_builder.py
accretion_cli/_templates/replication_listener.py
accretion_cli/_templates/source_region_core.py
accretion_cli/_templates/services/__init__.py
accretion_cli/_templates/services/awslambda.py
accretion_cli/_templates/services/iam.py
accretion_cli/_templates/services/sns.py
accretion_cli/_templates/services/stepfunctions.py
accretion_cli/_util/__init__.py
accretion_cli/_util/cloudformation.py
accretion_cli/_util/parameters.py
accretion_cli/_util/s3.py
accretion_cli/_util/step_functions.py
accretion_cli/_util/workers_zip.py
accretion_cli-0.1.0.dist-info/LICENSE
accretion_cli-0.1.0.dist-info/METADATA
accretion_cli-0.1.0.dist-info/WHEEL
accretion_cli-0.1.0.dist-info/entry_points.txt
accretion_cli-0.1.0.dist-info/top_level.txt
accretion_cli-0.1.0.dist-info/RECORD
